{
  "uid": "OneImlx.Shared.Attributes",
  "isEii": false,
  "isExtensionMethod": false,
  "children": [
    {
      "inClass": true,
      "typePropertyName": "inClass",
      "id": "classes",
      "children": [
        {
          "uid": "OneImlx.Shared.Attributes.ActionAttribute",
          "isExtensionMethod": false,
          "parent": "OneImlx.Shared.Attributes",
          "href": "OneImlx.Shared.Attributes.ActionAttribute.html",
          "name": [
            {
              "lang": "csharp",
              "value": "ActionAttribute"
            },
            {
              "lang": "vb",
              "value": "ActionAttribute"
            }
          ],
          "nameWithType": [
            {
              "lang": "csharp",
              "value": "ActionAttribute"
            },
            {
              "lang": "vb",
              "value": "ActionAttribute"
            }
          ],
          "fullName": [
            {
              "lang": "csharp",
              "value": "OneImlx.Shared.Attributes.ActionAttribute"
            },
            {
              "lang": "vb",
              "value": "OneImlx.Shared.Attributes.ActionAttribute"
            }
          ],
          "specName": [
            {
              "lang": "csharp",
              "value": "<xref uid=\"OneImlx.Shared.Attributes.ActionAttribute\" text=\"ActionAttribute\"/>"
            },
            {
              "lang": "vb",
              "value": "<xref uid=\"OneImlx.Shared.Attributes.ActionAttribute\" text=\"ActionAttribute\"/>"
            }
          ],
          "level": 0,
          "summary": "<p sourcefile=\"api/OneImlx.Shared.Attributes.ActionAttribute.yml\" sourcestartlinenumber=\"1\">An actionable attribute.</p>\n",
          "type": "class",
          "platform": null,
          "isEii": false,
          "docurl": "",
          "sourceurl": "",
          "description": "",
          "remarks": "",
          "conceptual": "",
          "syntax": "",
          "implements": "",
          "example": "",
          "seealso": [],
          "id": "OneImlx_Shared_Attributes_ActionAttribute",
          "hideTitleType": false,
          "hideSubtitle": false
        },
        {
          "uid": "OneImlx.Shared.Attributes.ArchitectureAttribute",
          "isExtensionMethod": false,
          "parent": "OneImlx.Shared.Attributes",
          "href": "OneImlx.Shared.Attributes.ArchitectureAttribute.html",
          "name": [
            {
              "lang": "csharp",
              "value": "ArchitectureAttribute"
            },
            {
              "lang": "vb",
              "value": "ArchitectureAttribute"
            }
          ],
          "nameWithType": [
            {
              "lang": "csharp",
              "value": "ArchitectureAttribute"
            },
            {
              "lang": "vb",
              "value": "ArchitectureAttribute"
            }
          ],
          "fullName": [
            {
              "lang": "csharp",
              "value": "OneImlx.Shared.Attributes.ArchitectureAttribute"
            },
            {
              "lang": "vb",
              "value": "OneImlx.Shared.Attributes.ArchitectureAttribute"
            }
          ],
          "specName": [
            {
              "lang": "csharp",
              "value": "<xref uid=\"OneImlx.Shared.Attributes.ArchitectureAttribute\" text=\"ArchitectureAttribute\"/>"
            },
            {
              "lang": "vb",
              "value": "<xref uid=\"OneImlx.Shared.Attributes.ArchitectureAttribute\" text=\"ArchitectureAttribute\"/>"
            }
          ],
          "level": 0,
          "summary": "<p sourcefile=\"api/OneImlx.Shared.Attributes.ArchitectureAttribute.yml\" sourcestartlinenumber=\"1\">Specifies that the target has an architectural comment that may be resolved in future releases. Applications can\nuse the target element, but the design may change in future releases including breaking changes.</p>\n",
          "type": "class",
          "platform": null,
          "isEii": false,
          "docurl": "",
          "sourceurl": "",
          "description": "",
          "remarks": "",
          "conceptual": "",
          "syntax": "",
          "implements": "",
          "example": "",
          "seealso": [],
          "id": "OneImlx_Shared_Attributes_ArchitectureAttribute",
          "hideTitleType": false,
          "hideSubtitle": false
        },
        {
          "uid": "OneImlx.Shared.Attributes.ConceptAttribute",
          "isExtensionMethod": false,
          "href": "OneImlx.Shared.Attributes.ConceptAttribute.html",
          "name": [
            {
              "lang": "csharp",
              "value": "ConceptAttribute"
            },
            {
              "lang": "vb",
              "value": "ConceptAttribute"
            }
          ],
          "nameWithType": [
            {
              "lang": "csharp",
              "value": "ConceptAttribute"
            },
            {
              "lang": "vb",
              "value": "ConceptAttribute"
            }
          ],
          "fullName": [
            {
              "lang": "csharp",
              "value": "OneImlx.Shared.Attributes.ConceptAttribute"
            },
            {
              "lang": "vb",
              "value": "OneImlx.Shared.Attributes.ConceptAttribute"
            }
          ],
          "specName": [
            {
              "lang": "csharp",
              "value": "<xref uid=\"OneImlx.Shared.Attributes.ConceptAttribute\" text=\"ConceptAttribute\"/>"
            },
            {
              "lang": "vb",
              "value": "<xref uid=\"OneImlx.Shared.Attributes.ConceptAttribute\" text=\"ConceptAttribute\"/>"
            }
          ],
          "level": 0,
          "summary": "<p sourcefile=\"api/OneImlx.Shared.Attributes.ConceptAttribute.yml\" sourcestartlinenumber=\"1\">Indicates that the target element represents a concept.</p>\n",
          "type": "class",
          "platform": null,
          "isEii": false,
          "docurl": "",
          "sourceurl": "",
          "description": "",
          "remarks": "",
          "conceptual": "",
          "syntax": "",
          "implements": "",
          "example": "",
          "seealso": [],
          "id": "OneImlx_Shared_Attributes_ConceptAttribute",
          "hideTitleType": false,
          "hideSubtitle": false
        },
        {
          "uid": "OneImlx.Shared.Attributes.FutureAttribute",
          "isExtensionMethod": false,
          "href": "OneImlx.Shared.Attributes.FutureAttribute.html",
          "name": [
            {
              "lang": "csharp",
              "value": "FutureAttribute"
            },
            {
              "lang": "vb",
              "value": "FutureAttribute"
            }
          ],
          "nameWithType": [
            {
              "lang": "csharp",
              "value": "FutureAttribute"
            },
            {
              "lang": "vb",
              "value": "FutureAttribute"
            }
          ],
          "fullName": [
            {
              "lang": "csharp",
              "value": "OneImlx.Shared.Attributes.FutureAttribute"
            },
            {
              "lang": "vb",
              "value": "OneImlx.Shared.Attributes.FutureAttribute"
            }
          ],
          "specName": [
            {
              "lang": "csharp",
              "value": "<xref uid=\"OneImlx.Shared.Attributes.FutureAttribute\" text=\"FutureAttribute\"/>"
            },
            {
              "lang": "vb",
              "value": "<xref uid=\"OneImlx.Shared.Attributes.FutureAttribute\" text=\"FutureAttribute\"/>"
            }
          ],
          "level": 0,
          "summary": "<p sourcefile=\"api/OneImlx.Shared.Attributes.FutureAttribute.yml\" sourcestartlinenumber=\"1\">Indicates a future capability or a feature request.</p>\n",
          "type": "class",
          "platform": null,
          "isEii": false,
          "docurl": "",
          "sourceurl": "",
          "description": "",
          "remarks": "",
          "conceptual": "",
          "syntax": "",
          "implements": "",
          "example": "",
          "seealso": [],
          "id": "OneImlx_Shared_Attributes_FutureAttribute",
          "hideTitleType": false,
          "hideSubtitle": false
        },
        {
          "uid": "OneImlx.Shared.Attributes.InternalInfrastructureAttribute",
          "isExtensionMethod": false,
          "parent": "OneImlx.Shared.Attributes",
          "href": "OneImlx.Shared.Attributes.InternalInfrastructureAttribute.html",
          "name": [
            {
              "lang": "csharp",
              "value": "InternalInfrastructureAttribute"
            },
            {
              "lang": "vb",
              "value": "InternalInfrastructureAttribute"
            }
          ],
          "nameWithType": [
            {
              "lang": "csharp",
              "value": "InternalInfrastructureAttribute"
            },
            {
              "lang": "vb",
              "value": "InternalInfrastructureAttribute"
            }
          ],
          "fullName": [
            {
              "lang": "csharp",
              "value": "OneImlx.Shared.Attributes.InternalInfrastructureAttribute"
            },
            {
              "lang": "vb",
              "value": "OneImlx.Shared.Attributes.InternalInfrastructureAttribute"
            }
          ],
          "specName": [
            {
              "lang": "csharp",
              "value": "<xref uid=\"OneImlx.Shared.Attributes.InternalInfrastructureAttribute\" text=\"InternalInfrastructureAttribute\"/>"
            },
            {
              "lang": "vb",
              "value": "<xref uid=\"OneImlx.Shared.Attributes.InternalInfrastructureAttribute\" text=\"InternalInfrastructureAttribute\"/>"
            }
          ],
          "level": 0,
          "summary": "<p sourcefile=\"api/OneImlx.Shared.Attributes.InternalInfrastructureAttribute.yml\" sourcestartlinenumber=\"1\">Indicates that the target is part of the internal infrastructure. Application should not use the target directly.</p>\n",
          "type": "class",
          "platform": null,
          "isEii": false,
          "docurl": "",
          "sourceurl": "",
          "description": "",
          "remarks": "",
          "conceptual": "",
          "syntax": "",
          "implements": "",
          "example": "",
          "seealso": [],
          "id": "OneImlx_Shared_Attributes_InternalInfrastructureAttribute",
          "hideTitleType": false,
          "hideSubtitle": false
        },
        {
          "uid": "OneImlx.Shared.Attributes.PerformanceAttribute",
          "isExtensionMethod": false,
          "parent": "OneImlx.Shared.Attributes",
          "href": "OneImlx.Shared.Attributes.PerformanceAttribute.html",
          "name": [
            {
              "lang": "csharp",
              "value": "PerformanceAttribute"
            },
            {
              "lang": "vb",
              "value": "PerformanceAttribute"
            }
          ],
          "nameWithType": [
            {
              "lang": "csharp",
              "value": "PerformanceAttribute"
            },
            {
              "lang": "vb",
              "value": "PerformanceAttribute"
            }
          ],
          "fullName": [
            {
              "lang": "csharp",
              "value": "OneImlx.Shared.Attributes.PerformanceAttribute"
            },
            {
              "lang": "vb",
              "value": "OneImlx.Shared.Attributes.PerformanceAttribute"
            }
          ],
          "specName": [
            {
              "lang": "csharp",
              "value": "<xref uid=\"OneImlx.Shared.Attributes.PerformanceAttribute\" text=\"PerformanceAttribute\"/>"
            },
            {
              "lang": "vb",
              "value": "<xref uid=\"OneImlx.Shared.Attributes.PerformanceAttribute\" text=\"PerformanceAttribute\"/>"
            }
          ],
          "level": 0,
          "summary": "<p sourcefile=\"api/OneImlx.Shared.Attributes.PerformanceAttribute.yml\" sourcestartlinenumber=\"1\">Specifies that the target has a performance comment that may be resolved in future releases. Applications can\nuse the target element, but the design may change in future releases including breaking changes.</p>\n",
          "type": "class",
          "platform": null,
          "isEii": false,
          "docurl": "",
          "sourceurl": "",
          "description": "",
          "remarks": "",
          "conceptual": "",
          "syntax": "",
          "implements": "",
          "example": "",
          "seealso": [],
          "id": "OneImlx_Shared_Attributes_PerformanceAttribute",
          "hideTitleType": false,
          "hideSubtitle": false
        },
        {
          "uid": "OneImlx.Shared.Attributes.RefactorAttribute",
          "isExtensionMethod": false,
          "parent": "OneImlx.Shared.Attributes",
          "href": "OneImlx.Shared.Attributes.RefactorAttribute.html",
          "name": [
            {
              "lang": "csharp",
              "value": "RefactorAttribute"
            },
            {
              "lang": "vb",
              "value": "RefactorAttribute"
            }
          ],
          "nameWithType": [
            {
              "lang": "csharp",
              "value": "RefactorAttribute"
            },
            {
              "lang": "vb",
              "value": "RefactorAttribute"
            }
          ],
          "fullName": [
            {
              "lang": "csharp",
              "value": "OneImlx.Shared.Attributes.RefactorAttribute"
            },
            {
              "lang": "vb",
              "value": "OneImlx.Shared.Attributes.RefactorAttribute"
            }
          ],
          "specName": [
            {
              "lang": "csharp",
              "value": "<xref uid=\"OneImlx.Shared.Attributes.RefactorAttribute\" text=\"RefactorAttribute\"/>"
            },
            {
              "lang": "vb",
              "value": "<xref uid=\"OneImlx.Shared.Attributes.RefactorAttribute\" text=\"RefactorAttribute\"/>"
            }
          ],
          "level": 0,
          "summary": "<p sourcefile=\"api/OneImlx.Shared.Attributes.RefactorAttribute.yml\" sourcestartlinenumber=\"1\">Specifies that the target should be re-factored. Applications can use the target element, but the design may\nchange in future releases including breaking changes.</p>\n",
          "type": "class",
          "platform": null,
          "isEii": false,
          "docurl": "",
          "sourceurl": "",
          "description": "",
          "remarks": "",
          "conceptual": "",
          "syntax": "",
          "implements": "",
          "example": "",
          "seealso": [],
          "id": "OneImlx_Shared_Attributes_RefactorAttribute",
          "hideTitleType": false,
          "hideSubtitle": false
        },
        {
          "uid": "OneImlx.Shared.Attributes.WriteApiAttribute",
          "isExtensionMethod": false,
          "href": "OneImlx.Shared.Attributes.WriteApiAttribute.html",
          "name": [
            {
              "lang": "csharp",
              "value": "WriteApiAttribute"
            },
            {
              "lang": "vb",
              "value": "WriteApiAttribute"
            }
          ],
          "nameWithType": [
            {
              "lang": "csharp",
              "value": "WriteApiAttribute"
            },
            {
              "lang": "vb",
              "value": "WriteApiAttribute"
            }
          ],
          "fullName": [
            {
              "lang": "csharp",
              "value": "OneImlx.Shared.Attributes.WriteApiAttribute"
            },
            {
              "lang": "vb",
              "value": "OneImlx.Shared.Attributes.WriteApiAttribute"
            }
          ],
          "specName": [
            {
              "lang": "csharp",
              "value": "<xref uid=\"OneImlx.Shared.Attributes.WriteApiAttribute\" text=\"WriteApiAttribute\"/>"
            },
            {
              "lang": "vb",
              "value": "<xref uid=\"OneImlx.Shared.Attributes.WriteApiAttribute\" text=\"WriteApiAttribute\"/>"
            }
          ],
          "level": 0,
          "summary": "<p sourcefile=\"api/OneImlx.Shared.Attributes.WriteApiAttribute.yml\" sourcestartlinenumber=\"1\">Indicates that the target element should add the relevant back-end API.</p>\n",
          "type": "class",
          "platform": null,
          "isEii": false,
          "docurl": "",
          "sourceurl": "",
          "description": "",
          "remarks": "",
          "conceptual": "",
          "syntax": "",
          "implements": "",
          "example": "",
          "seealso": [],
          "id": "OneImlx_Shared_Attributes_WriteApiAttribute",
          "hideTitleType": false,
          "hideSubtitle": false
        },
        {
          "uid": "OneImlx.Shared.Attributes.WriteDocumentationAttribute",
          "isExtensionMethod": false,
          "href": "OneImlx.Shared.Attributes.WriteDocumentationAttribute.html",
          "name": [
            {
              "lang": "csharp",
              "value": "WriteDocumentationAttribute"
            },
            {
              "lang": "vb",
              "value": "WriteDocumentationAttribute"
            }
          ],
          "nameWithType": [
            {
              "lang": "csharp",
              "value": "WriteDocumentationAttribute"
            },
            {
              "lang": "vb",
              "value": "WriteDocumentationAttribute"
            }
          ],
          "fullName": [
            {
              "lang": "csharp",
              "value": "OneImlx.Shared.Attributes.WriteDocumentationAttribute"
            },
            {
              "lang": "vb",
              "value": "OneImlx.Shared.Attributes.WriteDocumentationAttribute"
            }
          ],
          "specName": [
            {
              "lang": "csharp",
              "value": "<xref uid=\"OneImlx.Shared.Attributes.WriteDocumentationAttribute\" text=\"WriteDocumentationAttribute\"/>"
            },
            {
              "lang": "vb",
              "value": "<xref uid=\"OneImlx.Shared.Attributes.WriteDocumentationAttribute\" text=\"WriteDocumentationAttribute\"/>"
            }
          ],
          "level": 0,
          "summary": "<p sourcefile=\"api/OneImlx.Shared.Attributes.WriteDocumentationAttribute.yml\" sourcestartlinenumber=\"1\">Indicates that the target element requires documentation.</p>\n",
          "type": "class",
          "platform": null,
          "isEii": false,
          "docurl": "",
          "sourceurl": "",
          "description": "",
          "remarks": "",
          "conceptual": "",
          "syntax": "",
          "implements": "",
          "example": "",
          "seealso": [],
          "id": "OneImlx_Shared_Attributes_WriteDocumentationAttribute",
          "hideTitleType": false,
          "hideSubtitle": false
        },
        {
          "uid": "OneImlx.Shared.Attributes.WriteIntegrationTestAttribute",
          "isExtensionMethod": false,
          "href": "OneImlx.Shared.Attributes.WriteIntegrationTestAttribute.html",
          "name": [
            {
              "lang": "csharp",
              "value": "WriteIntegrationTestAttribute"
            },
            {
              "lang": "vb",
              "value": "WriteIntegrationTestAttribute"
            }
          ],
          "nameWithType": [
            {
              "lang": "csharp",
              "value": "WriteIntegrationTestAttribute"
            },
            {
              "lang": "vb",
              "value": "WriteIntegrationTestAttribute"
            }
          ],
          "fullName": [
            {
              "lang": "csharp",
              "value": "OneImlx.Shared.Attributes.WriteIntegrationTestAttribute"
            },
            {
              "lang": "vb",
              "value": "OneImlx.Shared.Attributes.WriteIntegrationTestAttribute"
            }
          ],
          "specName": [
            {
              "lang": "csharp",
              "value": "<xref uid=\"OneImlx.Shared.Attributes.WriteIntegrationTestAttribute\" text=\"WriteIntegrationTestAttribute\"/>"
            },
            {
              "lang": "vb",
              "value": "<xref uid=\"OneImlx.Shared.Attributes.WriteIntegrationTestAttribute\" text=\"WriteIntegrationTestAttribute\"/>"
            }
          ],
          "level": 0,
          "summary": "<p sourcefile=\"api/OneImlx.Shared.Attributes.WriteIntegrationTestAttribute.yml\" sourcestartlinenumber=\"1\">Indicates that the target element should have integration tests.</p>\n",
          "type": "class",
          "platform": null,
          "isEii": false,
          "docurl": "",
          "sourceurl": "",
          "description": "",
          "remarks": "",
          "conceptual": "",
          "syntax": "",
          "implements": "",
          "example": "",
          "seealso": [],
          "id": "OneImlx_Shared_Attributes_WriteIntegrationTestAttribute",
          "hideTitleType": false,
          "hideSubtitle": false
        },
        {
          "uid": "OneImlx.Shared.Attributes.WriteUnitTestAttribute",
          "isExtensionMethod": false,
          "href": "OneImlx.Shared.Attributes.WriteUnitTestAttribute.html",
          "name": [
            {
              "lang": "csharp",
              "value": "WriteUnitTestAttribute"
            },
            {
              "lang": "vb",
              "value": "WriteUnitTestAttribute"
            }
          ],
          "nameWithType": [
            {
              "lang": "csharp",
              "value": "WriteUnitTestAttribute"
            },
            {
              "lang": "vb",
              "value": "WriteUnitTestAttribute"
            }
          ],
          "fullName": [
            {
              "lang": "csharp",
              "value": "OneImlx.Shared.Attributes.WriteUnitTestAttribute"
            },
            {
              "lang": "vb",
              "value": "OneImlx.Shared.Attributes.WriteUnitTestAttribute"
            }
          ],
          "specName": [
            {
              "lang": "csharp",
              "value": "<xref uid=\"OneImlx.Shared.Attributes.WriteUnitTestAttribute\" text=\"WriteUnitTestAttribute\"/>"
            },
            {
              "lang": "vb",
              "value": "<xref uid=\"OneImlx.Shared.Attributes.WriteUnitTestAttribute\" text=\"WriteUnitTestAttribute\"/>"
            }
          ],
          "level": 0,
          "summary": "<p sourcefile=\"api/OneImlx.Shared.Attributes.WriteUnitTestAttribute.yml\" sourcestartlinenumber=\"1\">Indicates that the target element should have unit tests.</p>\n",
          "type": "class",
          "platform": null,
          "isEii": false,
          "docurl": "",
          "sourceurl": "",
          "description": "",
          "remarks": "",
          "conceptual": "",
          "syntax": "",
          "implements": "",
          "example": "",
          "seealso": [],
          "id": "OneImlx_Shared_Attributes_WriteUnitTestAttribute",
          "hideTitleType": false,
          "hideSubtitle": false
        }
      ]
    }
  ],
  "langs": [
    "csharp",
    "vb"
  ],
  "name": [
    {
      "lang": "csharp",
      "value": "OneImlx.Shared.Attributes"
    },
    {
      "lang": "vb",
      "value": "OneImlx.Shared.Attributes"
    }
  ],
  "nameWithType": [
    {
      "lang": "csharp",
      "value": "OneImlx.Shared.Attributes"
    },
    {
      "lang": "vb",
      "value": "OneImlx.Shared.Attributes"
    }
  ],
  "fullName": [
    {
      "lang": "csharp",
      "value": "OneImlx.Shared.Attributes"
    },
    {
      "lang": "vb",
      "value": "OneImlx.Shared.Attributes"
    }
  ],
  "type": "namespace",
  "assemblies": [
    "OneImlx.Shared"
  ],
  "level": 0,
  "_appFaviconPath": "images/favicon.ico",
  "_appFooter": "Copyright &copy; 2019-2025. Perpetual Intelligence&reg; L.L.C. All Rights Reserved.",
  "_appLogoPath": "images/logo.ico",
  "_enableSearch": true,
  "pdf": false,
  "pdfCoverPage": "pdf/cover.html",
  "pdfFileName": "oneimlx.pdf",
  "pdfTocPage": true,
  "_systemKeys": [
    "uid",
    "isEii",
    "isExtensionMethod",
    "parent",
    "children",
    "href",
    "langs",
    "name",
    "nameWithType",
    "fullName",
    "type",
    "source",
    "documentation",
    "assemblies",
    "namespace",
    "summary",
    "remarks",
    "example",
    "syntax",
    "overridden",
    "overload",
    "exceptions",
    "seealso",
    "see",
    "inheritance",
    "derivedClasses",
    "level",
    "implements",
    "inheritedMembers",
    "extensionMethods",
    "conceptual",
    "platform",
    "attributes",
    "additionalNotes"
  ],
  "_key": "api/OneImlx.Shared.Attributes.yml",
  "_navKey": "~/toc.yml",
  "_navPath": "toc.html",
  "_navRel": "../toc.html",
  "_path": "api/OneImlx.Shared.Attributes.html",
  "_rel": "../",
  "_tocKey": "~/api/toc.yml",
  "_tocPath": "api/toc.html",
  "_tocRel": "toc.html",
  "__global": {
    "namespacesInSubtitle": "Namespaces",
    "classesInSubtitle": "Classes",
    "structsInSubtitle": "Structs",
    "interfacesInSubtitle": "Interfaces",
    "enumsInSubtitle": "Enums",
    "delegatesInSubtitle": "Delegates",
    "constructorsInSubtitle": "Constructors",
    "fieldsInSubtitle": "Fields",
    "propertiesInSubtitle": "Properties",
    "methodsInSubtitle": "Methods",
    "eventsInSubtitle": "Events",
    "operatorsInSubtitle": "Operators",
    "eiisInSubtitle": "Explicit Interface Implementations",
    "functionsInSubtitle": "Functions",
    "variablesInSubtitle": "Variables",
    "typeAliasesInSubtitle": "Type Aliases",
    "membersInSubtitle": "Members",
    "improveThisDoc": "Edit this page",
    "viewSource": "View Source",
    "inheritance": "Inheritance",
    "derived": "Derived",
    "inheritedMembers": "Inherited Members",
    "package": "Package",
    "namespace": "Namespace",
    "assembly": "Assembly",
    "syntax": "Syntax",
    "overrides": "Overrides",
    "implements": "Implements",
    "remarks": "Remarks",
    "examples": "Examples",
    "seealso": "See Also",
    "declaration": "Declaration",
    "parameters": "Parameters",
    "typeParameters": "Type Parameters",
    "type": "Type",
    "name": "Name",
    "description": "Description",
    "returns": "Returns",
    "fieldValue": "Field Value",
    "propertyValue": "Property Value",
    "eventType": "Event Type",
    "variableValue": "Variable Value",
    "typeAliasType": "Type Alias Type",
    "exceptions": "Exceptions",
    "condition": "Condition",
    "extensionMethods": "Extension Methods",
    "note": "Note",
    "warning": "Warning",
    "tip": "Tip",
    "important": "Important",
    "caution": "Caution",
    "tocToggleButton": "Show / Hide Table of Contents",
    "tocFilter": "Filter by title",
    "search": "Search",
    "searchResults": "Search Results for",
    "searchResultsCount": "{count} results for \"{query}\"",
    "searchNoResults": "No results for \"{query}\"",
    "pageFirst": "First",
    "pagePrev": "Previous",
    "pageNext": "Next",
    "pageLast": "Last",
    "inThisArticle": "In this article",
    "nextArticle": "Next",
    "prevArticle": "Previous",
    "backToTop": "Back to top",
    "themeLight": "Light",
    "themeDark": "Dark",
    "themeAuto": "Auto",
    "changeTheme": "Change theme",
    "copy": "Copy",
    "downloadPdf": "Download PDF",
    "_shared": {}
  },
  "yamlmime": "ManagedReference",
  "docurl": "",
  "sourceurl": "",
  "summary": "",
  "description": "",
  "remarks": "",
  "conceptual": "",
  "syntax": "",
  "implements": "",
  "example": "",
  "seealso": [],
  "id": "OneImlx_Shared_Attributes",
  "hideTitleType": false,
  "hideSubtitle": false,
  "isNamespace": true,
  "_disableToc": false,
  "_disableNextArticle": true
}